wowool/config.py
wowool/diagnostic.py
wowool/error.py
wowool/pipeline.py
wowool/wow.py
wowool/annotation/__init__.py
wowool/annotation/annotation.py
wowool/annotation/annotation_list.py
wowool/annotation/concept.py
wowool/annotation/entity.py
wowool/annotation/paragraph.py
wowool/annotation/sentence.py
wowool/annotation/token.py
wowool/apps/info.py
wowool/common/utilities.py
wowool/common/pipeline/__init__.py
wowool/common/pipeline/objects.py
wowool/document/__init__.py
wowool/document/defines.py
wowool/document/document.py
wowool/document/document_interface.py
wowool/document/factory.py
wowool/document/serialize.py
wowool/document/analysis/analysis_parser.py
wowool/document/analysis/document.py
wowool/document/analysis/document_format_exception.py
wowool/document/analysis/text_analysis.py
wowool/document/analysis/utilities.py
wowool/document/analysis/apps/anonymizer.py
wowool/document/analysis/apps/chunks.py
wowool/document/analysis/apps/entity_graph.py
wowool/document/analysis/apps/lid.py
wowool/document/analysis/apps/sentiments.py
wowool/document/analysis/apps/themes.py
wowool/document/analysis/apps/topics.py
wowool/io/console/__init__.py
wowool/io/console/argument_parser.py
wowool/io/console/console.py
wowool/io/provider/__init__.py
wowool/io/provider/binary.py
wowool/io/provider/docx.py
wowool/io/provider/encoding.py
wowool/io/provider/factory.py
wowool/io/provider/file.py
wowool/io/provider/html_v2.py
wowool/io/provider/pdf_no_layout.py
wowool/io/provider/rtf.py
wowool/io/provider/str.py
wowool/string/__init__.py
wowool/tool/woc/create.py
wowool/utility/__init__.py
wowool/utility/default_arguments.py
wowool/utility/diagnostics.py
wowool/utility/method_registry.py
wowool/utility/numbers.py
wowool/utility/apps/decorators.py
wowool/utility/apps/yml_include.py
wowool/utility/csv/__init__.py
wowool/utility/iterators/__init__.py
wowool/utility/mime_type/mime_type.py
wowool/utility/path/__init__.py
wowool/utility/path/path.py
wowool/utility/text/cleanup.py
wowool_common-3.6.4.dist-info/METADATA
wowool_common-3.6.4.dist-info/WHEEL
wowool_common-3.6.4.dist-info/top_level.txt
wowool_common-3.6.4.dist-info/RECORD
