Metadata-Version: 2.1
Name: wowool-common
Version: 3.6.4
Summary: The Wowool Common Package
Home-page: https://www.wowool.com/
Author: wowool
Author-email: info@wowool.com
Requires-Python: >=3.11
Requires-Dist: python-magic
Requires-Dist: PyYAML
Requires-Dist: readability-lxml
Requires-Dist: lxml-html-clean
Requires-Dist: unidecode
Requires-Dist: beautifulsoup4
Requires-Dist: html5lib
